README.md
setup.cfg
setup.py
quotes/__init__.py
quotes/good_reads.py
tQuotes.egg-info/PKG-INFO
tQuotes.egg-info/SOURCES.txt
tQuotes.egg-info/dependency_links.txt
tQuotes.egg-info/requires.txt
tQuotes.egg-info/top_level.txt