Metadata-Version: 1.0
Name: tQuotes
Version: 0.0.4
Summary: A library to get quotes from www.goodread.com.
Home-page: https://github.com/Elyager/tQuotes
Author: Erik Ochoa
Author-email: elyager@gmail.com
License: MIT
Platform: UNKNOWN
